inkawuvp_vertigo_camera/__init__.py
inkawuvp_vertigo_camera/__main__.py
inkawuvp_vertigo_camera/camera_stream.py
inkawuvp_vertigo_camera-0.0.1a2.dist-info/METADATA
inkawuvp_vertigo_camera-0.0.1a2.dist-info/WHEEL
inkawuvp_vertigo_camera-0.0.1a2.dist-info/top_level.txt
inkawuvp_vertigo_camera-0.0.1a2.dist-info/RECORD
