Metadata-Version: 2.1
Name: inkawuvp-vertigo-camera
Version: 0.0.1a2
Summary: A small example package
Author-email: Alexandre Tuleu <alexandre.tuleu.2005@polytechnique.org>
License: GNU General Public License v3 (GPLv3)
Classifier: Programming Language :: Python :: 3
Classifier: License :: OSI Approved :: GNU General Public License v3 (GPLv3)
Classifier: License :: OSI Approved :: MIT License
Requires-Python: >=3.8
Requires-Dist: fastapi[standard]
Requires-Dist: pygobject
Provides-Extra: dev
Requires-Dist: black >=22.10 ; extra == 'dev'
Requires-Dist: pytest ; extra == 'dev'
Requires-Dist: PyGObject-stubs ; extra == 'dev'
